{
    "Wearables": [
        {
            "Selected": true,
            "BodyPart": "Body",
            "Name": "body001Dutch",
            "Icon": "bodyIcon001",
            "PortraitImage": "body001",
            "Stamina": 0,
            "Knowledge": 0,
            "Fitness": 0,
            "Charisma": 0
        },
        {
            "Selected": false,
            "BodyPart": "Body",
            "Name": "body002Dutch",
            "Icon": "bodyIcon002",
            "PortraitImage": "body002",
            "Stamina": 0,
            "Knowledge": 0,
            "Fitness": 0,
            "Charisma": 0
        },
        {
            "Selected": true,
            "BodyPart": "Face",
            "Name": "face001Dutch",
            "Icon": "faceIcon001",
            "PortraitImage": "face001",
            "Stamina": 0,
            "Knowledge": 0,
            "Fitness": 0,
            "Charisma": 0
        },
        {
            "Selected": false,
            "BodyPart": "Face",
            "Name": "face002Dutch",
            "Icon": "faceIcon002",
            "PortraitImage": "face002",
            "Stamina": 0,
            "Knowledge": 0,
            "Fitness": 0,
            "Charisma": 0
        },
        {
            "Selected": false,
            "BodyPart": "Face",
            "Name": "face003Dutch",
            "Icon": "faceIcon003",
            "PortraitImage": "face003",
            "Stamina": 0,
            "Knowledge": 0,
            "Fitness": 0,
            "Charisma": 0
        },
        {
            "Selected": false,
            "BodyPart": "HairDutch",
            "Name": "hair001",
            "Icon": "hairIcon001",
            "PortraitImage": "hair001",
            "Stamina": 0,
            "Knowledge": 0,
            "Fitness": 0,
            "Charisma": 0
        },
        {
            "Selected": false,
            "BodyPart": "HairDutch",
            "Name": "hair002",
            "Icon": "hairIcon002",
            "PortraitImage": "hair002",
            "Stamina": 0,
            "Knowledge": 0,
            "Fitness": 0,
            "Charisma": 0
        },
        {
            "Selected": false,
            "BodyPart": "HairDutch",
            "Name": "hair003",
            "Icon": "hairIcon003",
            "PortraitImage": "hair003",
            "Stamina": 0,
            "Knowledge": 0,
            "Fitness": 0,
            "Charisma": 0
        },
        {
            "Selected": false,
            "BodyPart": "HairDutch",
            "Name": "hair004",
            "Icon": "hairIcon004",
            "PortraitImage": "hair004",
            "Stamina": 0,
            "Knowledge": 0,
            "Fitness": 0,
            "Charisma": 0
        },
        {
            "Selected": false,
            "BodyPart": "Hair",
            "Name": "hair005Dutch",
            "Icon": "hairIcon005",
            "PortraitImage": "hair005",
            "Stamina": 0,
            "Knowledge": 0,
            "Fitness": 0,
            "Charisma": 0
        },
        {
            "Selected": false,
            "BodyPart": "Top",
            "Name": "top001Dutch",
            "Icon": "topIcon001",
            "PortraitImage": "top001",
            "Stamina": 0,
            "Knowledge": 0,
            "Fitness": 0,
            "Charisma": 0
        },
        {
            "Selected": false,
            "BodyPart": "Top",
            "Name": "top002Dutch",
            "Icon": "topIcon002",
            "PortraitImage": "top002",
            "Stamina": 0,
            "Knowledge": 0,
            "Fitness": 0,
            "Charisma": 0
        },
        {
            "Selected": false,
            "BodyPart": "Top",
            "Name": "top003Dutch",
            "Icon": "topIcon003",
            "PortraitImage": "top003",
            "Stamina": 0,
            "Knowledge": 0,
            "Fitness": 0,
            "Charisma": 0
        },
        {
            "Selected": false,
            "BodyPart": "Top",
            "Name": "top004Dutch",
            "Icon": "topIcon004",
            "PortraitImage": "top004",
            "Stamina": 0,
            "Knowledge": 0,
            "Fitness": 0,
            "Charisma": 0
        },
        {
            "Selected": false,
            "BodyPart": "Bot",
            "Name": "bot001Dutch",
            "Icon": "botIcon001",
            "PortraitImage": "bot001",
            "Stamina": 0,
            "Knowledge": 0,
            "Fitness": 0,
            "Charisma": 0
        },
        {
            "Selected": false,
            "BodyPart": "Bot",
            "Name": "bot002Dutch",
            "Icon": "botIcon002",
            "PortraitImage": "bot002",
            "Stamina": 0,
            "Knowledge": 0,
            "Fitness": 0,
            "Charisma": 0
        },
        {
            "Selected": false,
            "BodyPart": "Bot",
            "Name": "bot003Dutch",
            "Icon": "botIcon003",
            "PortraitImage": "bot003",
            "Stamina": 0,
            "Knowledge": 0,
            "Fitness": 0,
            "Charisma": 0
        },
        {
            "Selected": false,
            "BodyPart": "Bot",
            "Name": "bot004Dutch",
            "Icon": "botIcon004",
            "PortraitImage": "bot004",
            "Stamina": 0,
            "Knowledge": 0,
            "Fitness": 0,
            "Charisma": 0
        },
        {
            "Selected": false,
            "BodyPart": "Shoes",
            "Name": "shoes001Dutch",
            "Icon": "shoesIcon001",
            "PortraitImage": "shoes001",
            "Stamina": 0,
            "Knowledge": 0,
            "Fitness": 0,
            "Charisma": 0
        },
        {
            "Selected": false,
            "BodyPart": "Shoes",
            "Name": "shoes002Dutch",
            "Icon": "shoesIcon002",
            "PortraitImage": "shoes002",
            "Stamina": 0,
            "Knowledge": 0,
            "Fitness": 0,
            "Charisma": 0
        },
        {
            "Selected": false,
            "BodyPart": "Shoes",
            "Name": "shoes003Dutch",
            "Icon": "shoesIcon003",
            "PortraitImage": "shoes003",
            "Stamina": 0,
            "Knowledge": 0,
            "Fitness": 0,
            "Charisma": 0
        },
        {
            "Selected": false,
            "BodyPart": "Shoes",
            "Name": "shoes004Dutch",
            "Icon": "shoesIcon004",
            "PortraitImage": "shoes004",
            "Stamina": 0,
            "Knowledge": 0,
            "Fitness": 0,
            "Charisma": 0
        }
    ]
}